{
  "project_info": {
    "project_number": "424513949619",
    "project_id": "comisariatoproyecto",
    "storage_bucket": "comisariatoproyecto.firebasestorage.app"
  },
  "client": [
    {
      "client_info": {
        "mobilesdk_app_id": "1:424513949619:android:44f356e5782e95d68b05c6",
        "android_client_info": {
          "package_name": "com.example.comisariatoproyecto"
        }
      },
      "oauth_client": [],
      "api_key": [
        {
          "current_key": "AIzaSyA2WcnthAY9aEmAFMgqdvXxryTMT7yVzeM"
        }
      ],
      "services": {
        "appinvite_service": {
          "other_platform_oauth_client": []
        }
      }
    }
  ],
  "configuration_version": "1"
}